naas_abi_core/__init__.py
naas_abi_core/apps/api/api.py
naas_abi_core/apps/api/api_test.py
naas_abi_core/apps/api/openapi_doc.py
naas_abi_core/apps/mcp/Dockerfile.mcp
naas_abi_core/apps/mcp/mcp_server.py
naas_abi_core/apps/mcp/mcp_server_test.py
naas_abi_core/apps/terminal_agent/main.py
naas_abi_core/apps/terminal_agent/terminal_style.py
naas_abi_core/engine/Engine.py
naas_abi_core/engine/EngineProxy.py
naas_abi_core/engine/Engine_test.py
naas_abi_core/engine/IEngine.py
naas_abi_core/engine/conftest.py
naas_abi_core/engine/engine_configuration/EngineConfiguration.py
naas_abi_core/engine/engine_configuration/EngineConfiguration_Deploy.py
naas_abi_core/engine/engine_configuration/EngineConfiguration_GenericLoader.py
naas_abi_core/engine/engine_configuration/EngineConfiguration_ObjectStorageService.py
naas_abi_core/engine/engine_configuration/EngineConfiguration_ObjectStorageService_test.py
naas_abi_core/engine/engine_configuration/EngineConfiguration_SecretService.py
naas_abi_core/engine/engine_configuration/EngineConfiguration_SecretService_test.py
naas_abi_core/engine/engine_configuration/EngineConfiguration_TripleStoreService.py
naas_abi_core/engine/engine_configuration/EngineConfiguration_TripleStoreService_test.py
naas_abi_core/engine/engine_configuration/EngineConfiguration_VectorStoreService.py
naas_abi_core/engine/engine_configuration/EngineConfiguration_VectorStoreService_test.py
naas_abi_core/engine/engine_configuration/EngineConfiguration_test.py
naas_abi_core/engine/engine_configuration/utils/PydanticModelValidator.py
naas_abi_core/engine/engine_loaders/EngineModuleLoader.py
naas_abi_core/engine/engine_loaders/EngineOntologyLoader.py
naas_abi_core/engine/engine_loaders/EngineServiceLoader.py
naas_abi_core/integration/__init__.py
naas_abi_core/integration/integration.py
naas_abi_core/models/Model.py
naas_abi_core/models/OpenRouter.py
naas_abi_core/models/OpenRouter_test.py
naas_abi_core/module/Module.py
naas_abi_core/module/ModuleAgentLoader.py
naas_abi_core-1.7.1.dist-info/METADATA
naas_abi_core-1.7.1.dist-info/WHEEL
naas_abi_core-1.7.1.dist-info/entry_points.txt
naas_abi_core-1.7.1.dist-info/RECORD
